[
  {
    "ticker": "COST",
    "title": "COST: Costco | Consumer Staples | Consumer Staples Merchandise Retail",
    "filename": "COST_20250717.html",
    "timestamp": "17/07/2025 01:32",
    "summary": "קוסט מתחזקת: דיבידנד, צמיחה ומהלכים אסטרטגיים\nמגמות חיוביות בשוק\nמניית Costco Wholesale Corporation (NASDAQ: COST) עוברת תנודתיות חיובית, מונעת על ידי מספר גורמים משמעותיים. החברה, המפעילה רשת חנויות ...",
    "tags": [],
    "Security": "Costco",
    "GICS Sector": "Consumer Staples",
    "GICS Sub-Industry": "Consumer Staples Merchandise Retail",
    "Headquarters Location": "Issaquah, Washington",
    "Date added": "1993-10-01",
    "CIK": "909832",
    "Founded": "1976"
  },
  {
    "ticker": "AON",
    "title": "AON: Aon plc | Financials | Insurance Brokers",
    "filename": "AON_20250717.html",
    "timestamp": "17/07/2025 01:37",
    "summary": "אאון פלאנט (Aon plc) חושפת הזדמנויות ואתגרים בשוק הביטוח הגלובלי\nרקע עסקי\nאאון פלאנט, חברת ענק בתחום הביטוח והסיכון, נמצאת במוקד תשומת הלב של משקיעים לאחר סדרה של עדכונים משמעותיים. החברה, עם נוכחות ג...",
    "tags": [],
    "Security": "Aon plc",
    "GICS Sector": "Financials",
    "GICS Sub-Industry": "Insurance Brokers",
    "Headquarters Location": "London, United Kingdom",
    "Date added": "1996-04-23",
    "CIK": "315293",
    "Founded": "1982 (1919)"
  },
  {
    "ticker": "VZ",
    "title": "VZ: Verizon | Communication Services | Integrated Telecommunication S…",
    "filename": "VZ_20250717.html",
    "timestamp": "17/07/2025 01:45",
    "summary": "עתיד התקשורת: ויזרון מובילה את הדרך עם טכנולוגיה חדשנית\nתקציר:\nויזרון, חברת תקשורת מובילה, נמצאת במוקד תשומת הלב של המשקיעים בזכות ביצועים חזקים וחדשנות טכנולוגית. חדשות חיוביות על חוזים ממשלתיים, הרח...",
    "tags": [],
    "Security": "Verizon",
    "GICS Sector": "Communication Services",
    "GICS Sub-Industry": "Integrated Telecommunication Services",
    "Headquarters Location": "New York City, New York",
    "Date added": "1983-11-30",
    "CIK": "732712",
    "Founded": "1983 (1877)"
  },
  {
    "ticker": "MTB",
    "title": "MTB: M&T Bank | Financials | Regional Banks",
    "filename": "MTB_20250717.html",
    "timestamp": "17/07/2025 01:51",
    "summary": "מניית M&T בנק: תוצאות רבעוניות מעורבות והזדמנויות עתידיות\nמבוא\nמניית M&T בנק (MTB) עוברת תנודתיות לאחר פרסום התוצאות הרבעוניות האחרונות, אשר הציגו ביצועים מעורבים. בעוד שהבנק דיווח על גידול בהכנסות לא...",
    "tags": [],
    "Security": "M&T Bank",
    "GICS Sector": "Financials",
    "GICS Sub-Industry": "Regional Banks",
    "Headquarters Location": "Buffalo, New York",
    "Date added": "2004-02-23",
    "CIK": "36270",
    "Founded": "1856"
  },
  {
    "ticker": "WFC",
    "title": "WFC: Wells Fargo | Financials | Diversified Banks",
    "filename": "WFC_20250717.html",
    "timestamp": "17/07/2025 01:57",
    "summary": "ניתוח הביצועים של Wellsfargo ברבעון השני והשלכות עבור המשקיעים\nתנודתיות בשוק בעקבות תוצאות הרבעון\nניהולו של Wells Fargo (NYSE: WFC) משך את תשומת לבם של המשקיעים ברבעון השני של 2023, כאשר הנתונים הפיננ...",
    "tags": [],
    "Security": "Wells Fargo",
    "GICS Sector": "Financials",
    "GICS Sub-Industry": "Diversified Banks",
    "Headquarters Location": "San Francisco, California",
    "Date added": "1976-06-30",
    "CIK": "72971",
    "Founded": "1852"
  },
  {
    "ticker": "FAST",
    "title": "FAST: Fastenal | Industrials | Trading Companies & Distributors",
    "filename": "FAST_20250717.html",
    "timestamp": "17/07/2025 02:01",
    "summary": "דוארדש: ביצועים מעורבים תחת לחץ עלויות ועתיד לא יציב\nפתיחה:\nדוארדש (DoorDash), ענקית המשלוחים, חווה רבעון מעורב עם תוצאות פיננסיות חזקות אך דאגות מתמשכות לגבי עתידה. החברה דיווחה על הכנסות רבעוניות מע...",
    "tags": [],
    "Security": "Fastenal",
    "GICS Sector": "Industrials",
    "GICS Sub-Industry": "Trading Companies & Distributors",
    "Headquarters Location": "Winona, Minnesota",
    "Date added": "2008-09-15",
    "CIK": "815556",
    "Founded": "1967"
  }
]